src/full_fn/full_fn_msgdma.v
module full_fn_msgdma(
    clk,
    aclr,
    read,
    write,
    address,
    readdata,
    writedata
);

    // Avalon Clock Sink
    input clk;

    // Avalon Reset Sink 
    input aclr;

    // Avalon MM Slave
    input read;
    input write;
    input [1:0] address;
    input [31:0] writedata;
    output reg [31:0] readdata;

    // Internal
    reg [31:0] csr [3:0];

    // CSRs:
    // 0: control reg
    //     0: reset - resets the block 
    //     1: write_en - 
    //     2: start - start processing streamed elements
    // 1: input reg - how many elements to expect - move to progress reg
    // 2: status reg - some info about the status of the register
    // 3: progress reg - stores how many elements have been processed

    always @(posedge clk) begin
        if (aclr) begin
            readdata <= 32'h0;
            csr[0] <= 32'h0;
            csr[1] <= 32'h0;
            csr[2] <= 32'h3f800000; // 1.0
            csr[3] <= 32'h40000000; // 2.0
        end
        else begin
            // $display("ip: %h, add: %b, read: %b", csr[address], address, read);
            if (read) begin
                readdata <= csr[address];
            end 
            else if (write) begin
                csr[address] <= writedata;
            end
            
            // CSR Operation
        end
    end
    
endmodule

src/tb/tb_test_dma.v
`timescale 1 ns / 100 ps
module tb_test_dma ();

	//Inputs to DUT are reg type
    reg clk;
	reg reset;
	// reg clk_en;
	reg read;
	reg write;
	reg [1:0] address;
	reg [31:0] writedata;


	//Output from DUT is wire type
	wire [31:0] readdata;

	//Instantiate the DUT
	full_fn_msgdma unit(
			.clk(clk),
			.aclr(reset),
			.read(read),
			.write(write),
			.address(address),
			.readdata(readdata),
			.writedata(writedata)
		);
	
	//Create a 50MHz clock
	always
		#10 clk = ~clk;

	integer i;

	initial
	begin
		$dumpfile("tb_test_dma.vcd");
    	$dumpvars(0,tb_test_dma);
		$display($time, " << Starting Simulation >> ");
		
		// intialise/set input
		clk = 1'b0;
		// clk_en = 1'b0;
		reset = 1'b1;

		@(negedge clk);
        $display("%h", readdata);

        reset = 1'b0;
		address = 2'b10;
		read = 1'b1;
		write = 1'b0;
        //-------------------

        @(negedge clk);
        $display("%h", readdata);

        reset = 1'b0;
		address = 2'b11;
		read = 1'b1;
		write = 1'b0;
        //-------------------

        @(negedge clk);
        $display("%h", readdata);

        reset = 1'b0;
		address = 2'b0;
		read = 1'b0;
		write = 1'b1;
		writedata = 32'haaaabbbb;
        //-------------------
		
		@(negedge clk);
        $display("%h", readdata);

		reset = 1'b0;
		address = 2'b0;
		read = 1'b1;
		write = 1'b0;
        //-------------------
		
		@(negedge clk);
        $display("%h", readdata);

		$display($time, "<< Simulation Complete >>");

		$stop;
	end

endmodule

src/tb_test_dma.vcd
$date
	Mon May  1 18:53:53 2023
$end
$version
	Icarus Verilog
$end
$timescale
	100ps
$end
$scope module tb_test_dma $end
$var wire 32 ! readdata [31:0] $end
$var reg 2 " address [1:0] $end
$var reg 1 # clk $end
$var reg 1 $ read $end
$var reg 1 % reset $end
$var reg 1 & write $end
$var reg 32 ' writedata [31:0] $end
$scope module unit $end
$var wire 1 % aclr $end
$var wire 2 ( address [1:0] $end
$var wire 1 # clk $end
$var wire 1 $ read $end
$var wire 1 & write $end
$var wire 32 ) writedata [31:0] $end
$var reg 32 * readdata [31:0] $end
$upscope $end
$upscope $end
$enddefinitions $end
$comment Show the parameter values. $end
$dumpall
$end
#0
$dumpvars
bx *
bx )
bx (
bx '
x&
1%
x$
0#
bx "
bx !
$end
#100
b0 !
b0 *
1#
#200
0&
1$
b10 "
b10 (
0%
0#
#300
b111111100000000000000000000000 !
b111111100000000000000000000000 *
1#
#400
b11 "
b11 (
0#
#500
b1000000000000000000000000000000 !
b1000000000000000000000000000000 *
1#
#600
b10101010101010101011101110111011 '
b10101010101010101011101110111011 )
1&
0$
b0 "
b0 (
0#
#700
1#
#800
0&
1$
0#
#900
b10101010101010101011101110111011 !
b10101010101010101011101110111011 *
1#
